mlens_proto/__init__.py
mlens_proto/common_pb2.py
mlens_proto/events_pb2.py
mlens_proto/experiment_pb2.py
mlens_proto-1.0.0.dist-info/METADATA
mlens_proto-1.0.0.dist-info/WHEEL
mlens_proto-1.0.0.dist-info/top_level.txt
mlens_proto-1.0.0.dist-info/RECORD
