Metadata-Version: 2.4
Name: mlens-proto
Version: 1.0.0
Summary: MLens Protobuf schemas generated Python package
Author: MLens
License: MIT
Project-URL: Homepage, https://example.com
Classifier: Programming Language :: Python :: 3
Classifier: License :: OSI Approved :: MIT License
Classifier: Operating System :: OS Independent
Requires-Python: >=3.8
